[{"CiudadDePartida":"Jujuy","CiudadDeDestino":"Corrientes","FechaDeVuelo":"2023-05-27T13:11:44","CantidadAsientosDispTurista":11,"CantidadAsientosDispPremium":3,"CostoClasePremium":135,"CostoClaseTurista":100,"Pasajeros":[{"Dni":2222,"Edad":21,"Equipajes":[{"Tipo":"De bodega","Peso":5}],"Premium":false,"EquipajeDeMano":false,"EnVuelo":false,"Agregado":true,"Vacunado":false,"nombre":"Carlos","apellido":"Peralta"},{"Dni":14214124,"Edad":21,"Equipajes":[{"Tipo":"De bodega","Peso":2}],"Premium":false,"EquipajeDeMano":true,"EnVuelo":false,"Agregado":true,"Vacunado":false,"nombre":"Juan","apellido":"Ignacio"},{"Dni":111111,"Edad":111,"Equipajes":[{"Tipo":"De bodega","Peso":4},{"Tipo":"De bodega","Peso":1}],"Premium":true,"EquipajeDeMano":false,"EnVuelo":false,"Agregado":true,"Vacunado":false,"nombre":"Elias","apellido":"Veliz"}],"Estado":"No viaj\u00F3","Avion":{"Matricula":"AG3-24","CantidadAsientos":20,"CantidadDeBanios":2,"ServicioInternet":true,"ServicioComida":true,"CapacidadBodega":1000,"Disponible":false},"FechaDeLLegada":"2023-05-27T15:11:44","RecaudacionTotal":768.35,"AuxViaje":false,"AuxRealizado":false}]